camelCasing/__init__.py
camelCasing/camelCasing.py
camelcasing-0.1.3.dist-info/METADATA
camelcasing-0.1.3.dist-info/WHEEL
camelcasing-0.1.3.dist-info/licenses/LICENSE.txt
camelcasing-0.1.3.dist-info/RECORD
