Metadata-Version: 2.1
Name: camelCasing
Version: 0.1.3
Summary: Converts PascalCase or snake_case strings to camelCase.
Project-URL: Homepage, https://github.com/afogarty85/camelCasing
Project-URL: Bug Tracker, https://github.com/afogarty85/camelCasing/issues
Author-email: Andrew Fogarty <apf2bb@virginia.edu>
License-File: LICENSE.txt
Classifier: License :: OSI Approved :: MIT License
Classifier: Operating System :: OS Independent
Classifier: Programming Language :: Python :: 3
Requires-Python: >=3.7
